molsetrep/__init__.py
molsetrep/data/__init__.py
molsetrep/data/pdbbind_featurizer.py
molsetrep/encoders/__init__.py
molsetrep/encoders/common.py
molsetrep/encoders/dual_set_encoder.py
molsetrep/encoders/encoder.py
molsetrep/encoders/graph_encoder.py
molsetrep/encoders/ligand_prot_encoder.py
molsetrep/encoders/ligand_prot_pair_encoder.py
molsetrep/encoders/rxn_graph_encoder.py
molsetrep/encoders/rxn_set_encoder.py
molsetrep/encoders/single_set_encoder.py
molsetrep/internals/__init__.py
molsetrep/internals/data_manager.py
molsetrep/metrics/__init__.py
molsetrep/metrics/auprc.py
molsetrep/models/__init__.py
molsetrep/models/dual_sr.py
molsetrep/models/gine.py
molsetrep/models/gnn.py
molsetrep/models/mlp.py
molsetrep/models/set_rep.py
molsetrep/models/set_transformer.py
molsetrep/models/sr.py
molsetrep/models/sr_gnn.py
molsetrep/models/triple_sr.py
molsetrep/utils/__init__.py
molsetrep/utils/converters.py
molsetrep/utils/datasets.py
molsetrep-0.9.0.dist-info/LICENSE.txt
molsetrep-0.9.0.dist-info/METADATA
molsetrep-0.9.0.dist-info/WHEEL
molsetrep-0.9.0.dist-info/top_level.txt
molsetrep-0.9.0.dist-info/RECORD
