Metadata-Version: 2.1
Name: molsetrep
Version: 0.9.0
Summary: A library for molecular representation learning.
Home-page: https://github.com/pyscaffold/pyscaffold/
Author: Daniel Probst
Author-email: daenuprobst@gmail.com
License: MIT
Project-URL: Documentation, https://pyscaffold.org/
Platform: any
Classifier: Programming Language :: Python
Classifier: Intended Audience :: Science/Research
Classifier: License :: OSI Approved :: MIT License
Classifier: Topic :: Scientific/Engineering :: Artificial Intelligence
Classifier: Topic :: Scientific/Engineering :: Chemistry
Classifier: Topic :: Scientific/Engineering :: Bio-Informatics
License-File: LICENSE.txt
Requires-Dist: torch >=2.0.1
Requires-Dist: torch-geometric >=2.3.1
Requires-Dist: torchmetrics ==0.11.4
Requires-Dist: tqdm ==4.64.1
Requires-Dist: rdkit-pypi ==2022.9.5
Requires-Dist: networkx ==2.6.3
Requires-Dist: platformdirs ==2.6.2
Requires-Dist: typer ==0.9.0
Requires-Dist: lightning ==2.0.6
Requires-Dist: descriptastorus ==2.6.1
Requires-Dist: importlib-metadata ; python_version < "3.8"
Provides-Extra: testing
Requires-Dist: setuptools ; extra == 'testing'
Requires-Dist: pytest ; extra == 'testing'
Requires-Dist: pytest-cov ; extra == 'testing'
